<?xml version="1.0" encoding="UTF-8"?>
<Export generator="Cache" version="25">
  <Document name="dataset-countries.ZPM">
    <Module>
      <Name>dataset-countries</Name>
      <Description>Module imports the data of Country passengers in dc.data.Tinanic class</Description>
      <Version>1.0.1</Version>
      <Packaging>module</Packaging>
      <SourcesRoot>src</SourcesRoot>
      <Resource Name="dc.data.Country.CLS"/>
      <Resource Name="dc.data.CountryD.GBL"/>
    </Module>
  </Document>
</Export>